mir_ml_utils/__init__.py
mir_ml_utils/config.py
mir_ml_utils/data_handlers/__init__.py
mir_ml_utils/data_handlers/dataset_with_masks.py
mir_ml_utils/data_handlers/images_dataset.py
mir_ml_utils/easyfsl/__init__.py
mir_ml_utils/easyfsl/utils.py
mir_ml_utils/easyfsl/datasets/__init__.py
mir_ml_utils/easyfsl/datasets/cub.py
mir_ml_utils/easyfsl/datasets/danish_fungi.py
mir_ml_utils/easyfsl/datasets/default_configs.py
mir_ml_utils/easyfsl/datasets/easy_set.py
mir_ml_utils/easyfsl/datasets/few_shot_dataset.py
mir_ml_utils/easyfsl/datasets/mini_imagenet.py
mir_ml_utils/easyfsl/datasets/support_set_folder.py
mir_ml_utils/easyfsl/datasets/tiered_imagenet.py
mir_ml_utils/easyfsl/methods/__init__.py
mir_ml_utils/easyfsl/methods/bd_cspn.py
mir_ml_utils/easyfsl/methods/few_shot_classifier.py
mir_ml_utils/easyfsl/methods/finetune.py
mir_ml_utils/easyfsl/methods/matching_networks.py
mir_ml_utils/easyfsl/methods/prototypical_networks.py
mir_ml_utils/easyfsl/methods/relation_networks.py
mir_ml_utils/easyfsl/methods/tim.py
mir_ml_utils/easyfsl/methods/transductive_finetuning.py
mir_ml_utils/easyfsl/methods/utils.py
mir_ml_utils/easyfsl/modules/__init__.py
mir_ml_utils/easyfsl/modules/predesigned_modules.py
mir_ml_utils/easyfsl/modules/resnet.py
mir_ml_utils/easyfsl/samplers/__init__.py
mir_ml_utils/easyfsl/samplers/task_sampler.py
mir_ml_utils/factories/__init__.py
mir_ml_utils/factories/loss_function_factory.py
mir_ml_utils/factories/model_adaptor_factory.py
mir_ml_utils/factories/model_builder_factory.py
mir_ml_utils/factories/optimzer_factory.py
mir_ml_utils/loss_functions/__init__.py
mir_ml_utils/loss_functions/loss_function_result.py
mir_ml_utils/loss_functions/loss_function_wrapper.py
mir_ml_utils/mir_vision/__init__.py
mir_ml_utils/mir_vision/examples/python/README.md
mir_ml_utils/mir_vision/gallery/README.rst
mir_ml_utils/mir_vision/gallery/__init__.py
mir_ml_utils/mir_vision/gallery/plot_optical_flow.py
mir_ml_utils/mir_vision/gallery/plot_repurposing_annotations.py
mir_ml_utils-0.0.13.dist-info/METADATA
mir_ml_utils-0.0.13.dist-info/WHEEL
mir_ml_utils-0.0.13.dist-info/licenses/LICENSE
mir_ml_utils-0.0.13.dist-info/RECORD
