Metadata-Version: 2.1
Name: mir_ml_utils
Version: 0.0.13
Summary: Various utilities for machine learning training in Python 3. for the mir project
Project-URL: Homepage, https://github.com/Navalmartin/mir_ml_utils
Project-URL: Bug Tracker, https://github.com/Navalmartin/mir_ml_utils/issues
Author-email: Alexandros Giavaras <a.giavaras@gmail.com>
License-File: LICENSE
Classifier: License :: OSI Approved :: MIT License
Classifier: Operating System :: OS Independent
Classifier: Programming Language :: Python :: 3
Requires-Python: >=3.9
